sssweep/Analysis.py
sssweep/Sweeper.py
sssweep/__init__.py
sssweep/util.py
sssweep/web_viewer_gen.py
sssweep/resources/__init__.py
sssweep/resources/google-color.clr
sssweep/resources/google-favicon.ico
sssweep/resources/google-logo.png
sssweep/resources/hpe-color.clr
sssweep/resources/hpe-favicon.ico
sssweep/resources/hpe-logo.png
sssweep/resources/hpelabs-color.clr
sssweep/resources/hpelabs-favicon.ico
sssweep/resources/hpelabs-logo.png
sssweep/resources/nvidia-color.clr
sssweep/resources/nvidia-favicon.ico
sssweep/resources/nvidia-logo.png
sssweep/resources/ss-color.clr
sssweep/resources/ss-favicon.ico
sssweep/resources/ss-logo.png
sssweep-1.1.2.dist-info/LICENSE
sssweep-1.1.2.dist-info/METADATA
sssweep-1.1.2.dist-info/NOTICE
sssweep-1.1.2.dist-info/WHEEL
sssweep-1.1.2.dist-info/top_level.txt
sssweep-1.1.2.dist-info/RECORD
